{
  "4bc9bc63de414b03a2f73274fdb06157":
          {
          "row_merging_type": "mix",
          "table_data_boxes": [
            {
              "0": [
                {
                  "ocr_score": 0.993,
                  "word": "READING",
                  "coords": {
                    "y1": 773,
                    "x1": 626,
                    "y2": 800,
                    "x2": 746
                  }
                },
                {
                  "ocr_score": 0.993,
                  "word": "READING",
                  "coords": {
                    "y1": 774,
                    "x1": 806,
                    "y2": 800,
                    "x2": 926
                  }
                },
                {
                  "ocr_score": 0.996,
                  "word": "USAGE",
                  "coords": {
                    "y1": 774,
                    "x1": 980,
                    "y2": 800,
                    "x2": 1071
                  }
                }
              ],
              "1": [],
              "2": []
            },
            {
              "0": [
                {
                  "ocr_score": 0.997,
                  "word": "5,074",
                  "coords": {
                    "y1": 801,
                    "x1": 660,
                    "y2": 824,
                    "x2": 716
                  }
                },
                {
                  "ocr_score": 0.991,
                  "word": "4,794",
                  "coords": {
                    "y1": 799,
                    "x1": 840,
                    "y2": 823,
                    "x2": 896
                  }
                },
                {
                  "ocr_score": 0.994,
                  "word": "280,000",
                  "coords": {
                    "y1": 800,
                    "x1": 985,
                    "y2": 826,
                    "x2": 1069
                  }
                }
              ],
              "1": [
                {
                  "ocr_score": 0.994,
                  "word": "WATER",
                  "coords": {
                    "y1": 800,
                    "x1": 1109,
                    "y2": 824,
                    "x2": 1194
                  }
                }
              ],
              "2": [
                {
                  "ocr_score": 0.995,
                  "word": "1,372.26",
                  "coords": {
                    "y1": 797,
                    "x1": 1541,
                    "y2": 825,
                    "x2": 1624
                  }
                }
              ]
            },
            {
              "0": [],
              "1": [
                {
                  "ocr_score": 0.993,
                  "word": "SEWER",
                  "coords": {
                    "y1": 829,
                    "x1": 1108,
                    "y2": 854,
                    "x2": 1192
                  }
                }
              ],
              "2": [
                {
                  "ocr_score": 0.992,
                  "word": "1,149.78",
                  "coords": {
                    "y1": 829,
                    "x1": 1544,
                    "y2": 855,
                    "x2": 1622
                  }
                }
              ]
            },
            {
              "0": [],
              "1": [
                {
                  "ocr_score": 0.998,
                  "word": "TAX",
                  "coords": {
                    "y1": 856,
                    "x1": 1111,
                    "y2": 882,
                    "x2": 1158
                  }
                }
              ],
              "2": [
                {
                  "ocr_score": 0.991,
                  "word": "$0.00",
                  "coords": {
                    "y1": 859,
                    "x1": 1569,
                    "y2": 884,
                    "x2": 1621
                  }
                }
              ]
            }
          ],
          "post_remove_less_populated_lines": true,
          "column_mappings": {
            "0": [],
            "1": [
              "Description"
            ],
            "2": [
              "Amount"
            ]
          },
          "accuracy": 99.72,
          "table_identified": "charges_table",
          "document_id": "4bc9bc63de414b03a2f73274fdb06157",
          "predictions": [{"image_id": "0020001390005.pdf", "category_id": 1, "bbox": [148.20513916015625, 146.92034912109375, 260.6773376464844, 23.8343505859375], "score": 0.9972420930862427}, {"image_id": "0020001390005.pdf", "category_id": 0, "bbox": [271.3750915527344, 147.2156219482422, 100.30191040039062, 23.876449584960938], "score": 0.9992290735244751}, {"image_id": "0020001390005.pdf", "category_id": 0, "bbox": [372.77392578125, 147.16845703125, 31.1617431640625, 22.869705200195312], "score": 0.9982821941375732}],
          "execution_time": 0.12,
          "document_name": "0020001390005.pdf",
          "post_skip_lines_keywords": [],
          "table_data": [
            {
              "0": "READING READING USAGE",
              "1": "",
              "2": ""
            },
            {
              "0": "5,074 4,794 280,000 ",
              "1": "WATER ",
              "2": "1,372.26"
            },
            {
              "0": "",
              "1": "SEWER ",
              "2": "1,149.78"
            },
            {
              "0": "",
              "1": "TAX ",
              "2": "$0.00"
            }
          ],
          "width": 1700,
          "raw_table_data": [
            {
              "0": "READING READING USAGE ",
              "1": "",
              "2": ""
            },
            {
              "0": "5,074 4,794 280,000 ",
              "1": "WATER ",
              "2": "1,372.26 "
            },
            {
              "0": "",
              "1": "SEWER ",
              "2": "1,149.78 "
            },
            {
              "0": "",
              "1": "TAX ",
              "2": "$0.00 "
            }
          ],
          "folder_index": 0,
          "raw_table_data_boxes": [
            {
              "0": [
                {
                  "ocr_score": 0.993,
                  "word": "READING",
                  "coords": {
                    "y1": 773,
                    "x1": 626,
                    "y2": 800,
                    "x2": 746
                  }
                },
                {
                  "ocr_score": 0.993,
                  "word": "READING",
                  "coords": {
                    "y1": 774,
                    "x1": 806,
                    "y2": 800,
                    "x2": 926
                  }
                },
                {
                  "ocr_score": 0.996,
                  "word": "USAGE",
                  "coords": {
                    "y1": 774,
                    "x1": 980,
                    "y2": 800,
                    "x2": 1071
                  }
                }
              ],
              "1": [],
              "2": []
            },
            {
              "0": [
                {
                  "ocr_score": 0.997,
                  "word": "5,074",
                  "coords": {
                    "y1": 801,
                    "x1": 660,
                    "y2": 824,
                    "x2": 716
                  }
                },
                {
                  "ocr_score": 0.991,
                  "word": "4,794",
                  "coords": {
                    "y1": 799,
                    "x1": 840,
                    "y2": 823,
                    "x2": 896
                  }
                },
                {
                  "ocr_score": 0.994,
                  "word": "280,000",
                  "coords": {
                    "y1": 800,
                    "x1": 985,
                    "y2": 826,
                    "x2": 1069
                  }
                }
              ],
              "1": [
                {
                  "ocr_score": 0.994,
                  "word": "WATER",
                  "coords": {
                    "y1": 800,
                    "x1": 1109,
                    "y2": 824,
                    "x2": 1194
                  }
                }
              ],
              "2": [
                {
                  "ocr_score": 0.995,
                  "word": "1,372.26",
                  "coords": {
                    "y1": 797,
                    "x1": 1541,
                    "y2": 825,
                    "x2": 1624
                  }
                }
              ]
            },
            {
              "0": [],
              "1": [
                {
                  "ocr_score": 0.993,
                  "word": "SEWER",
                  "coords": {
                    "y1": 829,
                    "x1": 1108,
                    "y2": 854,
                    "x2": 1192
                  }
                }
              ],
              "2": [
                {
                  "ocr_score": 0.992,
                  "word": "1,149.78",
                  "coords": {
                    "y1": 829,
                    "x1": 1544,
                    "y2": 855,
                    "x2": 1622
                  }
                }
              ]
            },
            {
              "0": [],
              "1": [
                {
                  "ocr_score": 0.998,
                  "word": "TAX",
                  "coords": {
                    "y1": 856,
                    "x1": 1111,
                    "y2": 882,
                    "x2": 1158
                  }
                }
              ],
              "2": [
                {
                  "ocr_score": 0.991,
                  "word": "$0.00",
                  "coords": {
                    "y1": 859,
                    "x1": 1569,
                    "y2": 884,
                    "x2": 1621
                  }
                }
              ]
            }
          ],
          "ocr_line_coords": [
            [
              626,
              773,
              1071,
              800
            ],
            [
              660,
              797,
              1624,
              826
            ],
            [
              1108,
              829,
              1622,
              855
            ],
            [
              1111,
              856,
              1621,
              884
            ]
          ],
          "column_bounds": [
            {
              "y1": 771,
              "x1": 605,
              "y2": 902,
              "x2": 1108
            },
            {
              "y1": 771,
              "x1": 1108,
              "y2": 902,
              "x2": 1523
            },
            {
              "y1": 771,
              "x1": 1523,
              "y2": 902,
              "x2": 1670
            }
          ],
          "height": 2200,
          "character_count": 93
        },
  "9c38e1877aab403ea5c4b9a988f9c867":
          {
          "row_merging_type": "mix",
          "table_data_boxes": [
            {
              "0": [
                {
                  "ocr_score": 0.669,
                  "word": "CURRENT",
                  "coords": {
                    "y1": 733,
                    "x1": 619,
                    "y2": 761,
                    "x2": 754
                  }
                },
                {
                  "ocr_score": 0.993,
                  "word": "READING",
                  "coords": {
                    "y1": 773,
                    "x1": 626,
                    "y2": 800,
                    "x2": 746
                  }
                }
              ],
              "1": [
                {
                  "ocr_score": 0.994,
                  "word": "PREVIOUS",
                  "coords": {
                    "y1": 737,
                    "x1": 800,
                    "y2": 766,
                    "x2": 934
                  }
                },
                {
                  "ocr_score": 0.993,
                  "word": "READING",
                  "coords": {
                    "y1": 774,
                    "x1": 806,
                    "y2": 800,
                    "x2": 926
                  }
                }
              ],
              "2": [
                {
                  "ocr_score": 0.996,
                  "word": "USAGE",
                  "coords": {
                    "y1": 774,
                    "x1": 980,
                    "y2": 800,
                    "x2": 1071
                  }
                }
              ]
            },
            {
              "0": [
                {
                  "ocr_score": 0.997,
                  "word": "5,074",
                  "coords": {
                    "y1": 801,
                    "x1": 660,
                    "y2": 824,
                    "x2": 716
                  }
                }
              ],
              "1": [
                {
                  "ocr_score": 0.991,
                  "word": "4,794",
                  "coords": {
                    "y1": 799,
                    "x1": 840,
                    "y2": 823,
                    "x2": 896
                  }
                }
              ],
              "2": [
                {
                  "ocr_score": 0.994,
                  "word": "280,000",
                  "coords": {
                    "y1": 800,
                    "x1": 985,
                    "y2": 826,
                    "x2": 1069
                  }
                }
              ]
            }
          ],
          "post_remove_less_populated_lines": true,
          "column_mappings": {
            "0": [
              "Current Meter Reading"
            ],
            "1": [
              "Previous Meter Reading"
            ],
            "2": [
              "Usage"
            ]
          },
          "accuracy": 99.9,
          "table_identified": "meter_table",
          "document_id": "4bc9bc63de414b03a2f73274fdb06157",
          "predictions": [{"image_id": "0020001390005.pdf", "category_id": 1, "bbox": [138.4208984375, 136.0419158935547, 130.454345703125, 21.98028564453125], "score": 0.9990426898002625}, {"image_id": "0020001390005.pdf", "category_id": 0, "bbox": [234.05709838867188, 136.25413513183594, 31.365203857421875, 22.044967651367188], "score": 0.9997530579566956}, {"image_id": "0020001390005.pdf", "category_id": 0, "bbox": [187.09445190429688, 135.76083374023438, 47.79450988769531, 22.357040405273438], "score": 0.9993267059326172}, {"image_id": "0020001390005.pdf", "category_id": 0, "bbox": [144.74227905273438, 135.57955932617188, 43.534423828125, 23.089111328125], "score": 0.9991877675056458}],
          "execution_time": 0.17,
          "document_name": "0020001390005.pdf",
          "post_skip_lines_keywords": [],
          "table_data": [
            {
              "0": "CURRENT READING",
              "1": "PREVIOUS READING",
              "2": "USAGE"
            },
            {
              "0": "5,074 ",
              "1": "4,794 ",
              "2": "280,000"
            }
          ],
          "width": 1700,
          "raw_table_data": [
            {
              "0": "CURRENT ",
              "1": "PREVIOUS ",
              "2": ""
            },
            {
              "0": "READING ",
              "1": "READING ",
              "2": "USAGE "
            },
            {
              "0": "5,074 ",
              "1": "4,794 ",
              "2": "280,000 "
            }
          ],
          "folder_index": 0,
          "raw_table_data_boxes": [
            {
              "0": [
                {
                  "ocr_score": 0.669,
                  "word": "CURRENT",
                  "coords": {
                    "y1": 733,
                    "x1": 619,
                    "y2": 761,
                    "x2": 754
                  }
                }
              ],
              "1": [
                {
                  "ocr_score": 0.994,
                  "word": "PREVIOUS",
                  "coords": {
                    "y1": 737,
                    "x1": 800,
                    "y2": 766,
                    "x2": 934
                  }
                }
              ],
              "2": []
            },
            {
              "0": [
                {
                  "ocr_score": 0.993,
                  "word": "READING",
                  "coords": {
                    "y1": 773,
                    "x1": 626,
                    "y2": 800,
                    "x2": 746
                  }
                }
              ],
              "1": [
                {
                  "ocr_score": 0.993,
                  "word": "READING",
                  "coords": {
                    "y1": 774,
                    "x1": 806,
                    "y2": 800,
                    "x2": 926
                  }
                }
              ],
              "2": [
                {
                  "ocr_score": 0.996,
                  "word": "USAGE",
                  "coords": {
                    "y1": 774,
                    "x1": 980,
                    "y2": 800,
                    "x2": 1071
                  }
                }
              ]
            },
            {
              "0": [
                {
                  "ocr_score": 0.997,
                  "word": "5,074",
                  "coords": {
                    "y1": 801,
                    "x1": 660,
                    "y2": 824,
                    "x2": 716
                  }
                }
              ],
              "1": [
                {
                  "ocr_score": 0.991,
                  "word": "4,794",
                  "coords": {
                    "y1": 799,
                    "x1": 840,
                    "y2": 823,
                    "x2": 896
                  }
                }
              ],
              "2": [
                {
                  "ocr_score": 0.994,
                  "word": "280,000",
                  "coords": {
                    "y1": 800,
                    "x1": 985,
                    "y2": 826,
                    "x2": 1069
                  }
                }
              ]
            }
          ],
          "ocr_line_coords": [
            [
              619,
              733,
              934,
              766
            ],
            [
              626,
              773,
              1071,
              800
            ],
            [
              660,
              799,
              1069,
              826
            ]
          ],
          "column_bounds": [
            {
              "y1": 714,
              "x1": 565,
              "y2": 835,
              "x2": 764
            },
            {
              "y1": 714,
              "x1": 764,
              "y2": 835,
              "x2": 956
            },
            {
              "y1": 714,
              "x1": 956,
              "y2": 835,
              "x2": 1098
            }
          ],
          "height": 2200,
          "character_count": 67
        }
}