{
    "8d2bd09702df4bc78ac6f33332641785":
    {
        "row_merging_type": "mix",
        "table_data_boxes": [
          {
            "0": [
              {
                "ocr_score": 0.994,
                "word": "CURRENT",
                "coords": {
                  "y1": 726,
                  "x1": 625,
                  "y2": 755,
                  "x2": 754
                }
              },
              {
                "ocr_score": 0.993,
                "word": "READING",
                "coords": {
                  "y1": 763,
                  "x1": 625,
                  "y2": 790,
                  "x2": 744
                }
              }
            ],
            "1": [
              {
                "ocr_score": 0.996,
                "word": "PREVIOUS",
                "coords": {
                  "y1": 726,
                  "x1": 795,
                  "y2": 756,
                  "x2": 934
                }
              },
              {
                "ocr_score": 0.994,
                "word": "READING",
                "coords": {
                  "y1": 763,
                  "x1": 802,
                  "y2": 790,
                  "x2": 926
                }
              }
            ],
            "2": [
              {
                "ocr_score": 0.994,
                "word": "USAGE",
                "coords": {
                  "y1": 766,
                  "x1": 981,
                  "y2": 790,
                  "x2": 1070
                }
              }
            ]
          },
          {
            "0": [
              {
                "ocr_score": 0.996,
                "word": "51,507",
                "coords": {
                  "y1": 789,
                  "x1": 653,
                  "y2": 814,
                  "x2": 724
                }
              }
            ],
            "1": [
              {
                "ocr_score": 0.991,
                "word": "50,170",
                "coords": {
                  "y1": 787,
                  "x1": 832,
                  "y2": 814,
                  "x2": 904
                }
              }
            ],
            "2": [
              {
                "ocr_score": 0.994,
                "word": "1,337",
                "coords": {
                  "y1": 787,
                  "x1": 1003,
                  "y2": 813,
                  "x2": 1056
                }
              }
            ]
          },
          {
            "0": [
              {
                "ocr_score": 0.997,
                "word": "10,546",
                "coords": {
                  "y1": 818,
                  "x1": 653,
                  "y2": 845,
                  "x2": 724
                }
              }
            ],
            "1": [
              {
                "ocr_score": 0.97,
                "word": "9,984",
                "coords": {
                  "y1": 817,
                  "x1": 838,
                  "y2": 844,
                  "x2": 898
                }
              }
            ],
            "2": [
              {
                "ocr_score": 0.993,
                "word": "562",
                "coords": {
                  "y1": 816,
                  "x1": 1007,
                  "y2": 842,
                  "x2": 1050
                }
              }
            ]
          }
        ],
        "post_remove_less_populated_lines": true,
        "column_mappings": {
          "0": [
            "Current Meter Reading"
          ],
          "1": [
            "Previous Meter Reading"
          ],
          "2": [
            "Usage"
          ]
        },
        "accuracy": 99.88,
        "table_identified": "meter_table",
        "document_id": "f88155c93efa4bdba0ddadc606d06dbc",
        "predictions": """[{"image_id": "14076500.pdf", "category_id": 1, "bbox": [151.3348846435547, 134.25686645507812, 113.51261901855469, 29.535537719726562], "score": 0.9988420605659485}, {"image_id": "14076500.pdf", "category_id": 0, "bbox": [187.8829345703125, 133.72154235839844, 46.91752624511719, 30.257919311523438], "score": 0.9996746778488159}, {"image_id": "14076500.pdf", "category_id": 0, "bbox": [233.24554443359375, 134.5231170654297, 32.024261474609375, 27.949356079101562], "score": 0.9996309280395508}, {"image_id": "14076500.pdf", "category_id": 0, "bbox": [145.67889404296875, 133.55360412597656, 42.342742919921875, 30.040603637695312], "score": 0.999478280544281}]""",
        "execution_time": 0.11,
        "document_name": "14076500.pdf",
        "post_skip_lines_keywords": [],
        "table_data": [
          {
            "0": """CURRENT
READING""",
            "1": """PREVIOUS
READING""",
            "2": """
USAGE"""
          },
          {
            "0": "51,507 ",
            "1": "50,170 ",
            "2": "1,337"
          },
          {
            "0": "10,546 ",
            "1": "9,984 ",
            "2": "562"
          }
        ],
        "width": 1700,
        "raw_table_data": [
          {
            "0": "CURRENT ",
            "1": "PREVIOUS ",
            "2": ""
          },
          {
            "0": "READING ",
            "1": "READING ",
            "2": "USAGE "
          },
          {
            "0": "51,507 ",
            "1": "50,170 ",
            "2": "1,337 "
          },
          {
            "0": "10,546 ",
            "1": "9,984 ",
            "2": "562 "
          }
        ],
        "folder_index": 0,
        "raw_table_data_boxes": [
          {
            "0": [
              {
                "ocr_score": 0.994,
                "word": "CURRENT",
                "coords": {
                  "y1": 726,
                  "x1": 625,
                  "y2": 755,
                  "x2": 754
                }
              }
            ],
            "1": [
              {
                "ocr_score": 0.996,
                "word": "PREVIOUS",
                "coords": {
                  "y1": 726,
                  "x1": 795,
                  "y2": 756,
                  "x2": 934
                }
              }
            ],
            "2": []
          },
          {
            "0": [
              {
                "ocr_score": 0.993,
                "word": "READING",
                "coords": {
                  "y1": 763,
                  "x1": 625,
                  "y2": 790,
                  "x2": 744
                }
              }
            ],
            "1": [
              {
                "ocr_score": 0.994,
                "word": "READING",
                "coords": {
                  "y1": 763,
                  "x1": 802,
                  "y2": 790,
                  "x2": 926
                }
              }
            ],
            "2": [
              {
                "ocr_score": 0.994,
                "word": "USAGE",
                "coords": {
                  "y1": 766,
                  "x1": 981,
                  "y2": 790,
                  "x2": 1070
                }
              }
            ]
          },
          {
            "0": [
              {
                "ocr_score": 0.996,
                "word": "51,507",
                "coords": {
                  "y1": 789,
                  "x1": 653,
                  "y2": 814,
                  "x2": 724
                }
              }
            ],
            "1": [
              {
                "ocr_score": 0.991,
                "word": "50,170",
                "coords": {
                  "y1": 787,
                  "x1": 832,
                  "y2": 814,
                  "x2": 904
                }
              }
            ],
            "2": [
              {
                "ocr_score": 0.994,
                "word": "1,337",
                "coords": {
                  "y1": 787,
                  "x1": 1003,
                  "y2": 813,
                  "x2": 1056
                }
              }
            ]
          },
          {
            "0": [
              {
                "ocr_score": 0.997,
                "word": "10,546",
                "coords": {
                  "y1": 818,
                  "x1": 653,
                  "y2": 845,
                  "x2": 724
                }
              }
            ],
            "1": [
              {
                "ocr_score": 0.97,
                "word": "9,984",
                "coords": {
                  "y1": 817,
                  "x1": 838,
                  "y2": 844,
                  "x2": 898
                }
              }
            ],
            "2": [
              {
                "ocr_score": 0.993,
                "word": "562",
                "coords": {
                  "y1": 816,
                  "x1": 1007,
                  "y2": 842,
                  "x2": 1050
                }
              }
            ]
          }
        ],
        "ocr_line_coords": [
          [
            625,
            726,
            934,
            756
          ],
          [
            625,
            763,
            1070,
            790
          ],
          [
            653,
            787,
            1056,
            814
          ],
          [
            653,
            816,
            1050,
            845
          ]
        ],
        "column_bounds": [
          {
            "y1": 705,
            "x1": 595,
            "y2": 865,
            "x2": 767
          },
          {
            "y1": 705,
            "x1": 767,
            "y2": 865,
            "x2": 953
          },
          {
            "y1": 705,
            "x1": 953,
            "y2": 865,
            "x2": 1083
          }
        ],
        "height": 2200,
        "character_count": 87
    },
    "8ccfc4b5feb14e1cbaf9291c7abc8468":
    {
        "row_merging_type": "mix",
        "table_data_boxes": [
          {
            "0": [
              {
                "ocr_score": 0.991,
                "word": "50,170",
                "coords": {
                  "y1": 787,
                  "x1": 832,
                  "y2": 814,
                  "x2": 904
                }
              },
              {
                "ocr_score": 0.994,
                "word": "1,337",
                "coords": {
                  "y1": 787,
                  "x1": 1003,
                  "y2": 813,
                  "x2": 1056
                }
              }
            ],
            "1": [
              {
                "ocr_score": 0.994,
                "word": "WATER",
                "coords": {
                  "y1": 789,
                  "x1": 1110,
                  "y2": 814,
                  "x2": 1196
                }
              }
            ],
            "2": [
              {
                "ocr_score": 0.995,
                "word": "433.86",
                "coords": {
                  "y1": 791,
                  "x1": 1556,
                  "y2": 815,
                  "x2": 1625
                }
              }
            ]
          },
          {
            "0": [
              {
                "ocr_score": 0.97,
                "word": "9,984",
                "coords": {
                  "y1": 817,
                  "x1": 838,
                  "y2": 844,
                  "x2": 898
                }
              },
              {
                "ocr_score": 0.993,
                "word": "562",
                "coords": {
                  "y1": 816,
                  "x1": 1007,
                  "y2": 842,
                  "x2": 1050
                }
              }
            ],
            "1": [
              {
                "ocr_score": 0.998,
                "word": "WATER",
                "coords": {
                  "y1": 818,
                  "x1": 1110,
                  "y2": 845,
                  "x2": 1196
                }
              }
            ],
            "2": [
              {
                "ocr_score": 0.994,
                "word": "189.73",
                "coords": {
                  "y1": 816,
                  "x1": 1556,
                  "y2": 843,
                  "x2": 1622
                }
              }
            ]
          },
          {
            "0": [],
            "1": [
              {
                "ocr_score": 0.993,
                "word": "SEWER",
                "coords": {
                  "y1": 848,
                  "x1": 1109,
                  "y2": 875,
                  "x2": 1193
                }
              }
            ],
            "2": [
              {
                "ocr_score": 0.993,
                "word": "658.90",
                "coords": {
                  "y1": 849,
                  "x1": 1558,
                  "y2": 874,
                  "x2": 1625
                }
              }
            ]
          },
          {
            "0": [],
            "1": [
              {
                "ocr_score": 0.998,
                "word": "TUF",
                "coords": {
                  "y1": 878,
                  "x1": 1110,
                  "y2": 903,
                  "x2": 1158
                }
              }
            ],
            "2": [
              {
                "ocr_score": 0.988,
                "word": "8.00",
                "coords": {
                  "y1": 878,
                  "x1": 1580,
                  "y2": 903,
                  "x2": 1627
                }
              }
            ]
          }
        ],
        "post_remove_less_populated_lines": true,
        "column_mappings": {
          "0": [],
          "1": [
            "Description"
          ],
          "2": []
        },
        "accuracy": 99.48,
        "table_identified": "charges_table",
        "document_id": "f88155c93efa4bdba0ddadc606d06dbc",
        "predictions": """[{"image_id": "14076500.pdf", "category_id": 1, "bbox": [160.4629364013672, 146.01612854003906, 248.3821258544922, 26.371185302734375], "score": 0.9947858452796936}, {"image_id": "14076500.pdf", "category_id": 0, "bbox": [270.8263854980469, 145.88706970214844, 104.53173828125, 25.936737060546875], "score": 0.9995005130767822}, {"image_id": "14076500.pdf", "category_id": 0, "bbox": [375.2343444824219, 145.76698303222656, 28.32281494140625, 25.809188842773438], "score": 0.9988460540771484}]""",
        "execution_time": 0.11,
        "document_name": "14076500.pdf",
        "post_skip_lines_keywords": [],
        "table_data": [
          {
            "0": "50,170 1,337 ",
            "1": "WATER ",
            "2": "433.86"
          },
          {
            "0": "9,984 562 ",
            "1": "WATER ",
            "2": "189.73"
          },
          {
            "0": "",
            "1": "SEWER ",
            "2": "658.90"
          },
          {
            "0": "",
            "1": "TUF ",
            "2": "8.00"
          }
        ],
        "width": 1700,
        "raw_table_data": [
          {
            "0": "50,170 1,337 ",
            "1": "WATER ",
            "2": "433.86 "
          },
          {
            "0": "9,984 562 ",
            "1": "WATER ",
            "2": "189.73 "
          },
          {
            "0": "",
            "1": "SEWER ",
            "2": "658.90 "
          },
          {
            "0": "",
            "1": "TUF ",
            "2": "8.00 "
          }
        ],
        "folder_index": 0,
        "raw_table_data_boxes": [
          {
            "0": [
              {
                "ocr_score": 0.991,
                "word": "50,170",
                "coords": {
                  "y1": 787,
                  "x1": 832,
                  "y2": 814,
                  "x2": 904
                }
              },
              {
                "ocr_score": 0.994,
                "word": "1,337",
                "coords": {
                  "y1": 787,
                  "x1": 1003,
                  "y2": 813,
                  "x2": 1056
                }
              }
            ],
            "1": [
              {
                "ocr_score": 0.994,
                "word": "WATER",
                "coords": {
                  "y1": 789,
                  "x1": 1110,
                  "y2": 814,
                  "x2": 1196
                }
              }
            ],
            "2": [
              {
                "ocr_score": 0.995,
                "word": "433.86",
                "coords": {
                  "y1": 791,
                  "x1": 1556,
                  "y2": 815,
                  "x2": 1625
                }
              }
            ]
          },
          {
            "0": [
              {
                "ocr_score": 0.97,
                "word": "9,984",
                "coords": {
                  "y1": 817,
                  "x1": 838,
                  "y2": 844,
                  "x2": 898
                }
              },
              {
                "ocr_score": 0.993,
                "word": "562",
                "coords": {
                  "y1": 816,
                  "x1": 1007,
                  "y2": 842,
                  "x2": 1050
                }
              }
            ],
            "1": [
              {
                "ocr_score": 0.998,
                "word": "WATER",
                "coords": {
                  "y1": 818,
                  "x1": 1110,
                  "y2": 845,
                  "x2": 1196
                }
              }
            ],
            "2": [
              {
                "ocr_score": 0.994,
                "word": "189.73",
                "coords": {
                  "y1": 816,
                  "x1": 1556,
                  "y2": 843,
                  "x2": 1622
                }
              }
            ]
          },
          {
            "0": [],
            "1": [
              {
                "ocr_score": 0.993,
                "word": "SEWER",
                "coords": {
                  "y1": 848,
                  "x1": 1109,
                  "y2": 875,
                  "x2": 1193
                }
              }
            ],
            "2": [
              {
                "ocr_score": 0.993,
                "word": "658.90",
                "coords": {
                  "y1": 849,
                  "x1": 1558,
                  "y2": 874,
                  "x2": 1625
                }
              }
            ]
          },
          {
            "0": [],
            "1": [
              {
                "ocr_score": 0.998,
                "word": "TUF",
                "coords": {
                  "y1": 878,
                  "x1": 1110,
                  "y2": 903,
                  "x2": 1158
                }
              }
            ],
            "2": [
              {
                "ocr_score": 0.988,
                "word": "8.00",
                "coords": {
                  "y1": 878,
                  "x1": 1580,
                  "y2": 903,
                  "x2": 1627
                }
              }
            ]
          }
        ],
        "ocr_line_coords": [
          [
            832,
            787,
            1625,
            815
          ],
          [
            838,
            816,
            1622,
            845
          ],
          [
            1109,
            848,
            1625,
            875
          ],
          [
            1110,
            878,
            1627,
            903
          ]
        ],
        "column_bounds": [
          {
            "y1": 767,
            "x1": 655,
            "y2": 908,
            "x2": 1106
          },
          {
            "y1": 767,
            "x1": 1106,
            "y2": 908,
            "x2": 1533
          },
          {
            "y1": 767,
            "x1": 1533,
            "y2": 908,
            "x2": 1670
          }
        ],
        "height": 2200,
        "character_count": 82
    }
}